DeepLogTimedelta
