Metadata-Version: 2.1
Name: DeepLogTimedelta
Version: 0.2.2.1
Summary: a deeplog implementation for timedelta
Home-page: https://github.com/sasniy/DeeplogTimedelta
Author: Rustam Zhientaev
License: MIT
